{
  "id": "501109",
  "name": "奔赴未来的实验",
  "file": "奔赴未来的实验__501109.json",
  "alias": [
    "奔赴未来的实验"
  ],
  "category": "世界任务",
  "sections": [
    {
      "title": "剧情对话 1",
      "text": "与弗雷瑞斯对话\n弗雷瑞斯：从实验数据来看，这次的发明也圆满完成了。谢谢两位帮忙。\n谢妮：多谢啦。\n谢妮：你看，我就说会顺利吧。毕竟弗雷瑞斯前辈是这方面的天才，区区一个远距离操控炮台，做起来肯定是轻轻松松。\n弗雷瑞斯：是，是啊…\n谢妮：那抓紧时间，开始做下一个发明吧！正好我有个很感兴趣的东西！\n弗雷瑞斯：什么？\n谢妮：可以探索天空的浮空艇怎么样？\n弗雷瑞斯：呃…\n谢妮：或者能挖掘地底深处的超级钻头？\n弗雷瑞斯：哈…\n派蒙：感觉她在刁难弗雷瑞斯呢…\n【选项】旅行者：很难做到吧…\n谢妮：拒绝了枫丹科学院三次的弗雷瑞斯前辈，肯定能做出这些科学院做不出来的东西吧？\n弗雷瑞斯：那当然了。只能说…稍微有点棘手，不过问题不大。\n谢妮：唉，不过我突然又不想要这些了。飞到天上或者钻到地里，想想也很无聊。天上很冷，地下很闷，没什么好玩的东西。\n弗雷瑞斯：嗯，我也赞同。\n谢妮：那弗雷瑞斯前辈可以做一个平时能用到的发明吗？对了，我早上喜欢睡懒觉，可以请前辈帮我做个早餐自动烘焙机吗？\n派蒙：这个听起来倒是能做到。\n【选项】旅行者：她之前是故意的吧。\n弗雷瑞斯：好，我先想想怎么设计。\n谢妮：好耶，那我就当你答应啦。做不到的话，以后我的早餐就由弗雷瑞斯前辈本人来做好了！\n弗雷瑞斯：这是什么要求…总之放心吧，这种小发明我肯定能做出来。我可是这方面的「天才」啊。"
    }
  ],
  "searchText": "【剧情对话 1】\n与弗雷瑞斯对话\n弗雷瑞斯：从实验数据来看，这次的发明也圆满完成了。谢谢两位帮忙。\n谢妮：多谢啦。\n谢妮：你看，我就说会顺利吧。毕竟弗雷瑞斯前辈是这方面的天才，区区一个远距离操控炮台，做起来肯定是轻轻松松。\n弗雷瑞斯：是，是啊…\n谢妮：那抓紧时间，开始做下一个发明吧！正好我有个很感兴趣的东西！\n弗雷瑞斯：什么？\n谢妮：可以探索天空的浮空艇怎么样？\n弗雷瑞斯：呃…\n谢妮：或者能挖掘地底深处的超级钻头？\n弗雷瑞斯：哈…\n派蒙：感觉她在刁难弗雷瑞斯呢…\n【选项】旅行者：很难做到吧…\n谢妮：拒绝了枫丹科学院三次的弗雷瑞斯前辈，肯定能做出这些科学院做不出来的东西吧？\n弗雷瑞斯：那当然了。只能说…稍微有点棘手，不过问题不大。\n谢妮：唉，不过我突然又不想要这些了。飞到天上或者钻到地里，想想也很无聊。天上很冷，地下很闷，没什么好玩的东西。\n弗雷瑞斯：嗯，我也赞同。\n谢妮：那弗雷瑞斯前辈可以做一个平时能用到的发明吗？对了，我早上喜欢睡懒觉，可以请前辈帮我做个早餐自动烘焙机吗？\n派蒙：这个听起来倒是能做到。\n【选项】旅行者：她之前是故意的吧。\n弗雷瑞斯：好，我先想想怎么设计。\n谢妮：好耶，那我就当你答应啦。做不到的话，以后我的早餐就由弗雷瑞斯前辈本人来做好了！\n弗雷瑞斯：这是什么要求…总之放心吧，这种小发明我肯定能做出来。我可是这方面的「天才」啊。"
}